commodities_api/__init__.py
commodities_api/client.py
commodities_api-0.3.dist-info/METADATA
commodities_api-0.3.dist-info/WHEEL
commodities_api-0.3.dist-info/top_level.txt
commodities_api-0.3.dist-info/RECORD
