Metadata-Version: 2.1
Name: commodities-api
Version: 0.3
Summary: A Python package to get the latest commodities from the Commodities-API
Home-page: https://github.com/Zyla-Labs/pypi-commodities-api
Author: Commodities-API
Author-email: hello@commodities-api.com
Keywords: commodities-api,precious Commodities api,Commodities api,Commodities,precious Commodities,gold,silver,Platinum,Palladium,Ruthenium,Rhodium,forex data,rates,money,usd,eur,btc,forex api,gbp to usd,gbp to eur,eur to usd,api,currency api,exchange rate api,get currency rates api,currency rates php,usd to eur api,copper,nickel,aluminium,TIN,Zinc
